cartolafc/__init__.py
cartolafc/api.py
cartolafc/constants.py
cartolafc/errors.py
cartolafc/models.py
cartolafc/util.py
Python_CartolaFC-3.1.0.dist-info/LICENSE
Python_CartolaFC-3.1.0.dist-info/METADATA
Python_CartolaFC-3.1.0.dist-info/WHEEL
Python_CartolaFC-3.1.0.dist-info/top_level.txt
Python_CartolaFC-3.1.0.dist-info/RECORD
