Metadata-Version: 2.1
Name: Python-CartolaFC
Version: 3.1.0
Summary: Uma interface em Python para a API Rest do Cartola FC
Author-email: Vicente Ramos <sneto.vicente@gmail.com>
Project-URL: Homepage, https://github.com/vicenteneto/python-cartolafc
Project-URL: Bug Tracker, https://github.com/vicenteneto/python-cartolafc/issues
Keywords: python,cartolafc,api
Classifier: Development Status :: 5 - Production/Stable
Classifier: Intended Audience :: Developers
Classifier: License :: OSI Approved :: MIT License
Classifier: Operating System :: OS Independent
Classifier: Programming Language :: Python :: 3
Classifier: Topic :: Software Development :: Libraries :: Python Modules
Requires-Python: >=3.7
License-File: LICENSE
Requires-Dist: requests
